{
  "routes": [
    {
      "method": "GET",
      "path": "/divisions",
      "handler": "division.find",
      "config": {
        "policies": []
      }
    },
    {
      "method": "GET",
      "path": "/divisions/count",
      "handler": "division.count",
      "config": {
        "policies": []
      }
    },
    {
      "method": "GET",
      "path": "/divisions/:id",
      "handler": "division.findOne",
      "config": {
        "policies": []
      }
    },
    {
      "method": "POST",
      "path": "/divisions",
      "handler": "division.create",
      "config": {
        "policies": []
      }
    },
    {
      "method": "PUT",
      "path": "/divisions/:id",
      "handler": "division.update",
      "config": {
        "policies": []
      }
    },
    {
      "method": "DELETE",
      "path": "/divisions/:id",
      "handler": "division.delete",
      "config": {
        "policies": []
      }
    }
  ]
}
